msedge/__init__.py
msedge/selenium_tools/__init__.py
msedge/selenium_tools/options.py
msedge/selenium_tools/remote_connection.py
msedge/selenium_tools/service.py
msedge/selenium_tools/webdriver.py
msedge_selenium_tools-3.141.4.dist-info/LICENSE
msedge_selenium_tools-3.141.4.dist-info/METADATA
msedge_selenium_tools-3.141.4.dist-info/WHEEL
msedge_selenium_tools-3.141.4.dist-info/top_level.txt
msedge_selenium_tools-3.141.4.dist-info/RECORD
