Metadata-Version: 2.1
Name: msedge-selenium-tools
Version: 3.141.4
Summary: An updated EdgeDriver implementation for Selenium 3 with newly-added support for Microsoft Edge (Chromium).
Home-page: https://github.com/microsoft/edge-selenium-tools
Author: Microsoft Corporation
Author-email: EdgeDevToolsOSS@microsoft.com
License: Apache 2.0
Platform: UNKNOWN
Classifier: Development Status :: 5 - Production/Stable
Classifier: Intended Audience :: Developers
Classifier: License :: OSI Approved :: Apache Software License
Classifier: Operating System :: POSIX
Classifier: Operating System :: Microsoft :: Windows
Classifier: Operating System :: MacOS :: MacOS X
Classifier: Topic :: Software Development :: Testing
Classifier: Topic :: Software Development :: Libraries
Classifier: Programming Language :: Python
Classifier: Programming Language :: Python :: 2.7
Classifier: Programming Language :: Python :: 3.4
Classifier: Programming Language :: Python :: 3.5
Classifier: Programming Language :: Python :: 3.6
License-File: LICENSE
